Workbook
Name Slicer_Location1: #N/A
Name Slicer_Product_type: #N/A

Sheet supplychain_dataset
A1: Product type | B1: SKU | C1: Price | D1: Availability | E1: Number of products sold | F1: Revenue generated | G1: Customer demographics | H1: Stock levels | I1: Lead times | J1: Order quantities | K1: Shipping times | L1: Shipping carriers | M1: Shipping costs | N1: Supplier name | O1: Location | P1: Lead time | Q1: Production volumes | R1: Manufacturing lead time | S1: Manufacturing costs | T1: Inspection results | U1: defect -units | V1: pctdefect rate | W1: Defect rates | X1: Transportation modes | Y1: Routes | Z1: cost per unit | AA1: deliveryeff_hr | AB1: total_costs
A2: haircare | B2: SKU0 | C2: 69.808006 | D2: 55 | E2: 802 | F2: 8661.9968 | G2: Non-binary | H2: 58 | I2: 7 | J2: 96 | K2: 4 | L2: TransOceanic | M2: 2.9565721 | N2: Global Source Logistics | O2: Tech & R&D Center | P2: 18 | Q2: 673 | R2: 28 | S2: 14.190328 | T2: Pending | U2: =E2*W2 -> 1421.9068 | V2: 0.017729512 | W2: 1.7729512 | X2: Road | Y2: Indo-Pacific Corridor | Z2: 0.021085183 | AA2: 22 | AB2: 3474.9116
A3: skincare | B3: SKU1 | C3: 14.843523 | D3: 95 | E3: 736 | F3: 7460.9001 | G3: Female | H3: 53 | I3: 30 | J3: 37 | K3: 2 | L3: GlobalLogix | M3: 9.7165748 | N3: Global Source Logistics | O3: West Coast Hub (Port) | P3: 10 | Q3: 841 | R3: 12 | S3: 5.9306936 | T3: Pending | U3: =E3*W3 -> 451.4086 | V3: 0.006133269 | W3: 0.6133269 | X3: Air | Y3: Trans-Eurasian Hub | Z3: 0.0070519544 | AA3: 12 | AB3: 1698.3643
A4: haircare | B4: SKU2 | C4: 11.319683 | D4: 34 | E4: 8 | F4: 9577.7496 | G4: Unknown | H4: 1 | I4: 10 | J4: 88 | K4: 2 | L4: TransOceanic | M4: 8.0544793 | N4: Apex Manufacturing Corp | O4: South Asia Mfg Hub | P4: 24 | Q4: 461 | R4: 8 | S4: 60.251146 | T4: Pending | U4: =E4*W4 -> 23.912 | V4: 0.02989 | W4: 2.989 | X4: Rail | Y4: Americas Gateway | Z4: 0.13069663 | AA4: 26 | AB4: 3046.896
A5: skincare | B5: SKU3 | C5: 61.163343 | D5: 68 | E5: 83 | F5: 7766.8364 | G5: Non-binary | H5: 23 | I5: 13 | J5: 59 | K5: 6 | L5: SwiftParcel | M5: 1.7295686 | N5: Titan Industrial Group | O5: West Coast Hub (Port) | P5: 12 | Q5: 971 | R5: 27 | S5: 30.688019 | T5: Pending | U5: =E5*W5 -> 380.18919 | V5: 0.045805926 | W5: 4.5805926 | X5: Air | Y5: Americas Gateway | Z5: 0.031604551 | AA5: 18 | AB5: 709.60141
A6: skincare | B6: SKU4 | C6: 4.805496 | D6: 26 | E6: 871 | F6: 2686.5052 | G6: Non-binary | H6: 5 | I6: 3 | J6: 56 | K6: 8 | L6: GlobalLogix | M6: 3.8905479 | N6: Apex Manufacturing Corp | O6: East Gateway Hub | P6: 30 | Q6: 737 | R6: 7 | S6: 29.692467 | T6: Pass | U6: =E6*W6 -> 1694.9975 | V6: 0.019460361 | W6: 1.9460361 | X6: Road | Y6: Indo-Pacific Corridor | Z6: 0.040288287 | AA6: 38 | AB6: 3805.8695
A7: haircare | B7: SKU5 | C7: 1.699976 | D7: 87 | E7: 147 | F7: 2828.3487 | G7: Non-binary | H7: 90 | I7: 27 | J7: 66 | K7: 3 | L7: TransOceanic | M7: 4.4440989 | N7: Elite Quality Parts | O7: Tech & R&D Center | P7: 8 | Q7: 585 | R7: 8 | S7: 85.675963 | T7: Pass | U7: =E7*W7 -> 179.24919 | V7: 0.012193822 | W7: 1.2193822 | X7: Rail | Y7: Trans-Eurasian Hub | Z7: 0.14645464 | AA7: 11 | AB7: 4950.3924
A8: skincare | B8: SKU6 | C8: 4.0783329 | D8: 48 | E8: 65 | F8: 7823.4766 | G8: Male | H8: 11 | I8: 15 | J8: 58 | K8: 8 | L8: SwiftParcel | M8: 3.8807633 | N8: Global Source Logistics | O8: West Coast Hub (Port) | P8: 10 | Q8: 198 | R8: 11 | S8: 7.0578761 | T8: Pass | U8: =E8*W8 -> 8.5771039 | V8: 0.0013195544 | W8: 0.13195544 | X8: Sea | Y8: Americas Gateway | Z8: 0.035645839 | AA8: 18 | AB8: 846.35901
A9: cosmetics | B9: SKU7 | C9: 42.958384 | D9: 59 | E9: 426 | F9: 8496.1038 | G9: Female | H9: 93 | I9: 17 | J9: 11 | K9: 1 | L9: TransOceanic | M9: 2.3483388 | N9: Elite Quality Parts | O9: West Coast Hub (Port) | P9: 10 | Q9: 727 | R9: 27 | S9: 9.1668491 | T9: Pending | U9: =E9*W9 -> 904.17291 | V9: 0.021224716 | W9: 2.1224716 | X9: Air | Y9: Americas Gateway | Z9: 0.012609146 | AA9: 11 | AB9: 3014.4925
A10: cosmetics | B10: SKU8 | C10: 68.717597 | D10: 78 | E10: 150 | F10: 7517.3632 | G10: Female | H10: 5 | I10: 10 | J10: 15 | K10: 7 | L10: SwiftParcel | M10: 3.4047339 | N10: Elite Quality Parts | O10: West Coast Hub (Port) | P10: 21 | Q10: 953 | R10: 11 | S10: 68.184919 | T10: Pending | U10: =E10*W10 -> 108.33066 | V10: 0.007222044 | W10: 0.7222044 | X10: Sea | Y10: Indo-Pacific Corridor | Z10: 0.071547659 | AA10: 28 | AB10: 519.58124
A11: skincare | B11: SKU9 | C11: 64.015733 | D11: 35 | E11: 980 | F11: 4971.146 | G11: Unknown | H11: 14 | I11: 27 | J11: 83 | K11: 1 | L11: GlobalLogix | M11: 7.1666453 | N11: Precision Tech Solutions | O11: East Gateway Hub | P11: 18 | Q11: 374 | R11: 17 | S11: 27.107981 | T11: Pending | U11: =E11*W11 -> 2187.3003 | V11: 0.022319391 | W11: 2.2319391 | X11: Sea | Y11: Indo-Pacific Corridor | Z11: 0.072481232 | AA11: 19 | AB11: 2967.4013
A12: skincare | B12: SKU10 | C12: 15.707796 | D12: 11 | E12: 996 | F12: 2330.9658 | G12: Non-binary | H12: 51 | I12: 13 | J12: 80 | K12: 2 | L12: SwiftParcel | M12: 8.6732112 | N12: Titan Industrial Group | O12: South Asia Mfg Hub | P12: 29 | Q12: 921 | R12: 2 | S12: 38.072899 | T12: Fail | U12: =E12*W12 -> 344.64318 | V12: 0.0034602729 | W12: 0.34602729 | X12: Rail | Y12: Trans-Eurasian Hub | Z12: 0.041338652 | AA12: 31 | AB12: 1053.715
A13: skincare | B13: SKU11 | C13: 90.63546 | D13: 95 | E13: 960 | F13: 6099.9441 | G13: Female | H13: 46 | I13: 23 | J13: 60 | K13: 1 | L13: GlobalLogix | M13: 4.5239431 | N13: Precision Tech Solutions | O13: South Asia Mfg Hub | P13: 4 | Q13: 452 | R13: 10 | S13: 10.754273 | T13: Pass | U13: =E13*W13 -> 620.74038 | V13: 0.0064660456 | W13: 0.64660456 | X13: Road | Y13: Trans-Eurasian Hub | Z13: 0.023792639 | AA13: 5 | AB13: 2551.79
... A105: haircare | B105: SKU99 | C105: 68.517833 | D105: 17 | E105: 627 | F105: 9185.1858 | G105: Unknown | H105: 55 | I105: 8 | J105: 59 | K105: 6 | L105: TransOceanic | M105: 1.3110238 | N105: Precision Tech Solutions | O105: East Gateway Hub | P105: 11 | Q105: 176 | R105: 4 | S105: 1.9007622 | T105: Fail | U105: =E105*W105 -> 280.39065 | V105: 0.0044719402 | W105: 0.44719402 | X105: Air | Y105: Indo-Pacific Corridor | Z105: 0.010799785 | AA105: 17 | AB105: 1562.8714

Sheet supply_chain_clean_dataset
A1: Product type | B1: SKU | C1: Price | D1: theoretical_revenue | E1: discount/variance | F1: revenue varinace | G1: Availability | H1: Number of products sold | I1: Revenue generated | J1: Customer demographics | K1: Stock levels | L1: Lead times | M1: Order quantities | N1: Shipping times | O1: Shipping carriers | P1: Shipping costs | Q1: Supplier name | R1: Location | S1: Lead time | T1: Production volumes | U1: Manufacturing lead time | V1: Manufacturing costs | W1: Inspection results | X1: defect -units | Y1: pctdefect rate | Z1: Defect rates | AA1: Transportation modes | AB1: Routes | AC1: cost per unit | AD1: deliveryeff_hr | AE1: total_costs | AF1: net_profit | AG1: prfotmargin
A2: haircare | B2: SKU0 | C2: 69.808006 | D2: 55986.02 | E2: 47324.024 | F2: =IF(E2 > 0, "Discount Applied", "Premium Markup") -> Discount Applied | G2: 55 | H2: 802 | I2: 8661.9968 | J2: Non-binary | K2: 58 | L2: 7 | M2: 96 | N2: 4 | O2: TransOceanic | P2: 2.9565721 | Q2: Global Source Logistics | R2: Tech & R&D Center | S2: 18 | T2: 673 | U2: 28 | V2: 14.190328 | W2: Pending | X2: =H2*Z2 -> 1421.9068 | Y2: 0.017729512 | Z2: 1.7729512 | AA2: Road | AB2: Indo-Pacific Corridor | AC2: 0.021085183 | AD2: 22 | AE2: 3474.9116 | AF2: 5187.0852 | AG2: 0.5988325
A3: skincare | B3: SKU1 | C3: 14.843523 | D3: 10924.833 | E3: 3463.9331 | F3: =IF(E3 > 0, "Discount Applied", "Premium Markup") -> Discount Applied | G3: 95 | H3: 736 | I3: 7460.9001 | J3: Female | K3: 53 | L3: 30 | M3: 37 | N3: 2 | O3: GlobalLogix | P3: 9.7165748 | Q3: Global Source Logistics | R3: West Coast Hub (Port) | S3: 10 | T3: 841 | U3: 12 | V3: 5.9306936 | W3: Pending | X3: =H3*Z3 -> 451.4086 | Y3: 0.006133269 | Z3: 0.6133269 | AA3: Air | AB3: Trans-Eurasian Hub | AC3: 0.0070519544 | AD3: 12 | AE3: 1698.3643 | AF3: 5762.5357 | AG3: 0.77236468
A4: haircare | B4: SKU2 | C4: 11.319683 | D4: 90.557466 | E4: -9487.1922 | F4: =IF(E4 > 0, "Discount Applied", "Premium Markup") -> Premium Markup | G4: 34 | H4: 8 | I4: 9577.7496 | J4: Unknown | K4: 1 | L4: 10 | M4: 88 | N4: 2 | O4: TransOceanic | P4: 8.0544793 | Q4: Apex Manufacturing Corp | R4: South Asia Mfg Hub | S4: 24 | T4: 461 | U4: 8 | V4: 60.251146 | W4: Pending | X4: =H4*Z4 -> 23.912 | Y4: 0.02989 | Z4: 2.989 | AA4: Rail | AB4: Americas Gateway | AC4: 0.13069663 | AD4: 26 | AE4: 3046.896 | AF4: 6530.8536 | AG4: 0.68187767
A5: skincare | B5: SKU3 | C5: 61.163343 | D5: 5076.5575 | E5: -2690.279 | F5: =IF(E5 > 0, "Discount Applied", "Premium Markup") -> Premium Markup | G5: 68 | H5: 83 | I5: 7766.8364 | J5: Non-binary | K5: 23 | L5: 13 | M5: 59 | N5: 6 | O5: SwiftParcel | P5: 1.7295686 | Q5: Titan Industrial Group | R5: West Coast Hub (Port) | S5: 12 | T5: 971 | U5: 27 | V5: 30.688019 | W5: Pending | X5: =H5*Z5 -> 380.18919 | Y5: 0.045805926 | Z5: 4.5805926 | AA5: Air | AB5: Americas Gateway | AC5: 0.031604551 | AD5: 18 | AE5: 709.60141 | AF5: 7057.235 | AG5: 0.90863701
A6: skincare | B6: SKU4 | C6: 4.805496 | D6: 4185.587 | E6: 1499.0819 | F6: =IF(E6 > 0, "Discount Applied", "Premium Markup") -> Discount Applied | G6: 26 | H6: 871 | I6: 2686.5052 | J6: Non-binary | K6: 5 | L6: 3 | M6: 56 | N6: 8 | O6: GlobalLogix | P6: 3.8905479 | Q6: Apex Manufacturing Corp | R6: East Gateway Hub | S6: 30 | T6: 737 | U6: 7 | V6: 29.692467 | W6: Pass | X6: =H6*Z6 -> 1694.9975 | Y6: 0.019460361 | Z6: 1.9460361 | AA6: Road | AB6: Indo-Pacific Corridor | AC6: 0.040288287 | AD6: 38 | AE6: 3805.8695 | AF6: -1119.3644 | AG6: -0.41666192
A7: haircare | B7: SKU5 | C7: 1.699976 | D7: 249.89647 | E7: -2578.4523 | F7: =IF(E7 > 0, "Discount Applied", "Premium Markup") -> Premium Markup | G7: 87 | H7: 147 | I7: 2828.3487 | J7: Non-binary | K7: 90 | L7: 27 | M7: 66 | N7: 3 | O7: TransOceanic | P7: 4.4440989 | Q7: Elite Quality Parts | R7: Tech & R&D Center | S7: 8 | T7: 585 | U7: 8 | V7: 85.675963 | W7: Pass | X7: =H7*Z7 -> 179.24919 | Y7: 0.012193822 | Z7: 1.2193822 | AA7: Rail | AB7: Trans-Eurasian Hub | AC7: 0.14645464 | AD7: 11 | AE7: 4950.3924 | AF7: -2122.0436 | AG7: -0.75027651
A8: skincare | B8: SKU6 | C8: 4.0783329 | D8: 265.09164 | E8: -7558.3849 | F8: =IF(E8 > 0, "Discount Applied", "Premium Markup") -> Premium Markup | G8: 48 | H8: 65 | I8: 7823.4766 | J8: Male | K8: 11 | L8: 15 | M8: 58 | N8: 8 | O8: SwiftParcel | P8: 3.8807633 | Q8: Global Source Logistics | R8: West Coast Hub (Port) | S8: 10 | T8: 198 | U8: 11 | V8: 7.0578761 | W8: Pass | X8: =H8*Z8 -> 8.5771039 | Y8: 0.0013195544 | Z8: 0.13195544 | AA8: Sea | AB8: Americas Gateway | AC8: 0.035645839 | AD8: 18 | AE8: 846.35901 | AF8: 6977.1176 | AG8: 0.89181804
A9: cosmetics | B9: SKU7 | C9: 42.958384 | D9: 18300.272 | E9: 9804.1679 | F9: =IF(E9 > 0, "Discount Applied", "Premium Markup") -> Discount Applied | G9: 59 | H9: 426 | I9: 8496.1038 | J9: Female | K9: 93 | L9: 17 | M9: 11 | N9: 1 | O9: TransOceanic | P9: 2.3483388 | Q9: Elite Quality Parts | R9: West Coast Hub (Port) | S9: 10 | T9: 727 | U9: 27 | V9: 9.1668491 | W9: Pending | X9: =H9*Z9 -> 904.17291 | Y9: 0.021224716 | Z9: 2.1224716 | AA9: Air | AB9: Americas Gateway | AC9: 0.012609146 | AD9: 11 | AE9: 3014.4925 | AF9: 5481.6113 | AG9: 0.64519119
A10: cosmetics | B10: SKU8 | C10: 68.717597 | D10: 10307.64 | E10: 2790.2763 | F10: =IF(E10 > 0, "Discount Applied", "Premium Markup") -> Discount Applied | G10: 78 | H10: 150 | I10: 7517.3632 | J10: Female | K10: 5 | L10: 10 | M10: 15 | N10: 7 | O10: SwiftParcel | P10: 3.4047339 | Q10: Elite Quality Parts | R10: West Coast Hub (Port) | S10: 21 | T10: 953 | U10: 11 | V10: 68.184919 | W10: Pending | X10: =H10*Z10 -> 108.33066 | Y10: 0.007222044 | Z10: 0.7222044 | AA10: Sea | AB10: Indo-Pacific Corridor | AC10: 0.071547659 | AD10: 28 | AE10: 519.58124 | AF10: 6997.782 | AG10: 0.93088251
A11: skincare | B11: SKU9 | C11: 64.015733 | D11: 62735.418 | E11: 57764.272 | F11: =IF(E11 > 0, "Discount Applied", "Premium Markup") -> Discount Applied | G11: 35 | H11: 980 | I11: 4971.146 | J11: Unknown | K11: 14 | L11: 27 | M11: 83 | N11: 1 | O11: GlobalLogix | P11: 7.1666453 | Q11: Precision Tech Solutions | R11: East Gateway Hub | S11: 18 | T11: 374 | U11: 17 | V11: 27.107981 | W11: Pending | X11: =H11*Z11 -> 2187.3003 | Y11: 0.022319391 | Z11: 2.2319391 | AA11: Sea | AB11: Indo-Pacific Corridor | AC11: 0.072481232 | AD11: 19 | AE11: 2967.4013 | AF11: 2003.7447 | AG11: 0.40307501
A12: skincare | B12: SKU10 | C12: 15.707796 | D12: 15644.964 | E12: 13313.999 | F12: =IF(E12 > 0, "Discount Applied", "Premium Markup") -> Discount Applied | G12: 11 | H12: 996 | I12: 2330.9658 | J12: Non-binary | K12: 51 | L12: 13 | M12: 80 | N12: 2 | O12: SwiftParcel | P12: 8.6732112 | Q12: Titan Industrial Group | R12: South Asia Mfg Hub | S12: 29 | T12: 921 | U12: 2 | V12: 38.072899 | W12: Fail | X12: =H12*Z12 -> 344.64318 | Y12: 0.0034602729 | Z12: 0.34602729 | AA12: Rail | AB12: Trans-Eurasian Hub | AC12: 0.041338652 | AD12: 31 | AE12: 1053.715 | AF12: 1277.2508 | AG12: 0.54794916
A13: skincare | B13: SKU11 | C13: 90.63546 | D13: 87010.042 | E13: 80910.097 | F13: =IF(E13 > 0, "Discount Applied", "Premium Markup") -> Discount Applied | G13: 95 | H13: 960 | I13: 6099.9441 | J13: Female | K13: 46 | L13: 23 | M13: 60 | N13: 1 | O13: GlobalLogix | P13: 4.5239431 | Q13: Precision Tech Solutions | R13: South Asia Mfg Hub | S13: 4 | T13: 452 | U13: 10 | V13: 10.754273 | W13: Pass | X13: =H13*Z13 -> 620.74038 | Y13: 0.0064660456 | Z13: 0.64660456 | AA13: Road | AB13: Trans-Eurasian Hub | AC13: 0.023792639 | AD13: 5 | AE13: 2551.79 | AF13: 3548.1541 | AG13: 0.58166994
... A101: haircare | B101: SKU99 | C101: 68.517833 | D101: 42960.681 | E101: 33775.495 | F101: =IF(E101 > 0, "Discount Applied", "Premium Markup") -> Discount Applied | G101: 17 | H101: 627 | I101: 9185.1858 | J101: Unknown | K101: 55 | L101: 8 | M101: 59 | N101: 6 | O101: TransOceanic | P101: 1.3110238 | Q101: Precision Tech Solutions | R101: East Gateway Hub | S101: 11 | T101: 176 | U101: 4 | V101: 1.9007622 | W101: Fail | X101: =H101*Z101 -> 280.39065 | Y101: 0.0044719402 | Z101: 0.44719402 | AA101: Air | AB101: Indo-Pacific Corridor | AC101: 0.010799785 | AD101: 17 | AE101: 1562.8714 | AF101: 7622.3145 | AG101: 0.82984869

Sheet kpis
B3: reve | C3: proft | D3: avgprofit mrgin | E3: sold | F3: avg defect | G3: defc prod | H3: defect rate
B4: =SUM(supplychain_dataset!F:F) -> 599337.68 | C4: =SUM(supply_chain_clean_dataset!AF:AF) -> 312981.93 | D4: =AVERAGE(supply_chain_clean_dataset!AG:AG) -> 0.30002951 | E4: =SUM(supplychain_dataset!E:E) -> 47272 | F4: =AVERAGE(supplychain_dataset!W:W) -> 2.2924734 | G4: =SUM(supplychain_dataset!U:U) -> 105404.63 | H4: =F4/100 -> 0.022924734

Sheet operatinal & quality pivots
AI2: Row Labels | AJ2: Sum of Defect rates
AI3: Apex Manufacturing Corp | AJ3: 0.26803917
AI4: Precision Tech Solutions | AJ4: 0.20454237
AI5: Titan Industrial Group | AJ5: 0.18553287
AI6: Elite Quality Parts | AJ6: 0.18035995
AI7: Global Source Logistics | AJ7: 0.16152564
AI8: Grand Total | AJ8: 1
B14: Sum of Defect rates
B15: 227.7158
AH25: Row Labels | AI25: Sum of pctdefect rate
AH26: Road | AI26: 0.76007216
AH27: Rail | AI27: 0.64926789
AH28: Air | AI28: 0.47422012
AH29: Sea | AI29: 0.39359782
AH30: Grand Total | AI30: 2.277158
AC36: Row Labels | AD36: Average of Lead times
AC37: Elite Quality Parts | AD37: 17
AC38: Apex Manufacturing Corp | AD38: 16.777778
AC39: Precision Tech Solutions | AD39: 16.227273
AC40: Titan Industrial Group | AD40: 14.722222
AC41: Global Source Logistics | AD41: 14.333333
AC42: Grand Total | AD42: 15.96

Sheet profitmrg by hub pivot 
A2: Row Labels | B2: Average of prfotmargin
A3: West Coast Hub (Port) | B3: 0.5703957
A4: Northern Logistics Node | B4: 0.3204611
A5: East Gateway Hub | B5: 0.28855211
A6: Tech & R&D Center | B6: 0.19900888
A7: South Asia Mfg Hub | B7: 0.09256832
A8: Grand Total | B8: 0.30002951

Sheet product perform pivots
A27: Row Labels | B27: Sum of net_profit | C27: Sum of Revenue generated
A28: cosmetics | B28: 94814.152 | C28: 161521.27
A29: haircare | B29: 78829.357 | C29: 174455.39
A30: skincare | B30: 139338.42 | C30: 241628.16
A31: Grand Total | B31: 312981.93 | C31: 577604.82

Sheet dashboard

Sheet shipping cost vs time pivot
A2: Row Labels | B2: Average of Shipping costs | C2: Average of Shipping times
A3: GlobalLogix | B3: 5.5549225 | C3: 6.1428571
A4: SwiftParcel | B4: 5.5992916 | C4: 6.0344828
A5: TransOceanic | B5: 5.509247 | C5: 5.3023256
A6: Grand Total | B6: 5.5481491 | C6: 5.75
A22: Row Labels | B22: Sum of Number of products sold
A23: Unknown | B23: 15211
A24: Female | B24: 12801
A25: Non-binary | B25: 10580
A26: Male | B26: 7507
A27: Grand Total | B27: 46099
